easyT/__init__.py
easyT/file_generator.py
easyT/initialization.py
easyT/manager.py
easyT/platforms.py
easyT/rates.py
easyT/tick.py
easyT/timeframe.py
easyT/trade.py
tests/__init__.py
tests/conftest.py
tests/test_initialization.py
tests/test_manager.py
tests/test_rates.py
tests/test_tick.py
tests/test_timeframe.py
tests/test_trade.py
easyT-0.0.4.dist-info/LICENSE
easyT-0.0.4.dist-info/METADATA
easyT-0.0.4.dist-info/WHEEL
easyT-0.0.4.dist-info/entry_points.txt
easyT-0.0.4.dist-info/top_level.txt
easyT-0.0.4.dist-info/RECORD
