Metadata-Version: 2.1
Name: easyT
Version: 0.0.4
Home-page: https://github.com/Joaopeuko/easyT
Author: Joao Paulo Euko
License: MIT
Keywords: binance,spot,algotrading,cryptocurrency,automatic trade,automated trade
License-File: LICENSE
Requires-Dist: pandas
Requires-Dist: pytest
Requires-Dist: coverage
Requires-Dist: setuptools
Requires-Dist: pytest-cov
Requires-Dist: python-dotenv
Requires-Dist: python-dateutil
Requires-Dist: supportLibEasyT
Requires-Dist: binancespoteasyt
Requires-Dist: metatrader5easyt
